lance_namespace/__init__.py
lance_namespace/errors.py
lance_namespace/py.typed
lance_namespace/tests/__init__.py
lance_namespace/tests/test_namespace.py
lance_namespace-0.4.4.dist-info/METADATA
lance_namespace-0.4.4.dist-info/WHEEL
lance_namespace-0.4.4.dist-info/RECORD
