Metadata-Version: 2.4
Name: lance-namespace
Version: 0.4.4
Summary: Lance Namespace interface and plugin registry
Project-URL: Repository, https://github.com/lance-format/lance-namespace
Project-URL: Documentation, https://lance.org/format/namespace/
Author-email: LanceDB Devs <dev@lancedb.com>
License: Apache-2.0
Keywords: lance,lancedb,namespace,vector-database
Requires-Python: >=3.8
Requires-Dist: lance-namespace-urllib3-client==0.4.4
